pystas
