Metadata-Version: 1.1
Name: pystas
Version: 0.8.9
Summary: Track function calls and get basic statistics
Home-page: https://bitbucket.org/tenuki/pystas
Author: david weil (tenuki)
Author-email: tenuki@gmail.com
License: GNU General Public License v3.0
Platform: UNKNOWN
Classifier: Development Status :: 4 - Beta
Classifier: Intended Audience :: Developers
Classifier: Programming Language :: Python :: 2
Classifier: Programming Language :: Python :: 3
